Workbook

Sheet 假设
A1: 假设与口径（唯一参数源）
A2: 淡橙色为可调参数。修改后全表自动重算。
A4: 参数 | B4: 值 | C4: 单位 | D4: 说明
A5: 月净利目标 | B5: 20000 | C5: 元 | D5: 目标已更新：3 个月内成型为月入 2W
A6: 到账率 | B6: =1-B8-B9 -> 0.86 | C6: 比例 | D6: =1 − 平台服务费 − 退款损耗 -> #N/A
A7: 每月天数 | B7: 30 | C7: 天
A8: 平台服务费 | B8: 0.02 | C8: 比例 | D8: 虚拟商品常规服务费；免佣期可低至 0.6%
A9: 退款损耗 | B9: 0.12 | C9: 比例 | D9: 虚拟商品退款普遍；退款还会压制店铺分→流量
A10: 投流保守 CAC | B10: 20 | C10: 元/单 | D10: CPC 0.8 元 ÷ 点击→下单 4%
A11: 投流乐观 CAC | B11: 50 | C11: 元/单 | D11: CPC 2 元 ÷ 点击→下单 4%
A12: 付费单量占比 | B12: 0.4 | C12: 比例 | D12: 40% 单量来自付费流量；其余靠内容自然流
A14: 自动结论（随参数变化）
A15: 达到 2W 需要的毛销售额 | B15: =ROUND($B$5/B6,0) -> 23256 | D15: 因为净额 = 销售额 × 到账率，所以销售额必须放大
A16: 在 99 元客单下需要的单数 | B16: =ROUND($B$5/(99*B6),0) -> 235
A17: 若 40% 单量靠投流（CAC 35 元） | B17: =ROUND($B$5/(99*B6)*B12*AVERAGE(B10,B11),0) -> 3289 | D17: 这笔钱必须从净利里出
A18: 扣掉投流后实际净利 | B18: =$B$5-B16 -> 19765 | D18: 低于 2W 的差额
A19: 结论 | B19: =IF(B17>=target,"纯自然流 + 99 元客单即可达标","投流会吃掉 "&TEXT(B16,"#,##0")&" 元：2W 净利只能靠自然流 + 提客单实现，不能靠买量") -> #NAME? | D19: 这是本模型最重要的一条判断

Sheet 目标换算
A1: 月入 2W：不同客单需要多少单？
A2: 这一张表解释了为什么必须提客单 —— 在 29.9 元价格带上目标不成立。
A4: 客单档位 | B4: 客单价 | C4: 净额/单 | D4: 需成交单数/月 | E4: 日均单量 | F4: 付费单量 | G4: 投流支出(取CAC中值) | H4: 净利(扣投流) | I4: 是否达标
A5: 1 单件资料 | B5: 29.9 | C5: =B5*假设!$B$6 -> 25.714 | D5: =ROUNDUP(假设!$B$5/C5,0) -> 778 | E5: =ROUND(D5/假设!$B$7,1) -> 25.9 | F5: =ROUND(D5*假设!$B$12,0) -> 311 | G5: =F5*AVERAGE(假设!$B$10,假设!$B$11) -> 10885 | H5: =ROUND(D5*C5-G5,0) -> 9120 | I5: =IF(H5>=假设!$B$5,"达标（自然流口径）","差 "&TEXT(假设!$B$5-H5,"#,##0")&" 元") -> 差 10,880 元
A6: 小组合 | B6: 49.9 | C6: =B6*假设!$B$6 -> 42.914 | D6: =ROUNDUP(假设!$B$5/C6,0) -> 467 | E6: =ROUND(D6/假设!$B$7,1) -> 15.6 | F6: =ROUND(D6*假设!$B$12,0) -> 187 | G6: =F6*AVERAGE(假设!$B$10,假设!$B$11) -> 6545 | H6: =ROUND(D6*C6-G6,0) -> 13496 | I6: =IF(H6>=假设!$B$5,"达标（自然流口径）","差 "&TEXT(假设!$B$5-H6,"#,##0")&" 元") -> 差 6,504 元
A7: 全流程包（首批） | B7: 99 | C7: =B7*假设!$B$6 -> 85.14 | D7: =ROUNDUP(假设!$B$5/C7,0) -> 235 | E7: =ROUND(D7/假设!$B$7,1) -> 7.8 | F7: =ROUND(D7*假设!$B$12,0) -> 94 | G7: =F7*AVERAGE(假设!$B$10,假设!$B$11) -> 3290 | H7: =ROUND(D7*C7-G7,0) -> 16718 | I7: =IF(H7>=假设!$B$5,"达标（自然流口径）","差 "&TEXT(假设!$B$5-H7,"#,##0")&" 元") -> 差 3,282 元
A8: 全流程包（稳定） | B8: 149 | C8: =B8*假设!$B$6 -> 128.14 | D8: =ROUNDUP(假设!$B$5/C8,0) -> 157 | E8: =ROUND(D8/假设!$B$7,1) -> 5.2 | F8: =ROUND(D8*假设!$B$12,0) -> 63 | G8: =F8*AVERAGE(假设!$B$10,假设!$B$11) -> 2205 | H8: =ROUND(D8*C8-G8,0) -> 17913 | I8: =IF(H8>=假设!$B$5,"达标（自然流口径）","差 "&TEXT(假设!$B$5-H8,"#,##0")&" 元") -> 差 2,087 元
A9: 含 1v1 服务 | B9: 199 | C9: =B9*假设!$B$6 -> 171.14 | D9: =ROUNDUP(假设!$B$5/C9,0) -> 117 | E9: =ROUND(D9/假设!$B$7,1) -> 3.9 | F9: =ROUND(D9*假设!$B$12,0) -> 47 | G9: =F9*AVERAGE(假设!$B$10,假设!$B$11) -> 1645 | H9: =ROUND(D9*C9-G9,0) -> 18378 | I9: =IF(H9>=假设!$B$5,"达标（自然流口径）","差 "&TEXT(假设!$B$5-H9,"#,##0")&" 元") -> 差 1,622 元
A10: 陪跑服务 | B10: 399 | C10: =B10*假设!$B$6 -> 343.14 | D10: =ROUNDUP(假设!$B$5/C10,0) -> 59 | E10: =ROUND(D10/假设!$B$7,1) -> 2 | F10: =ROUND(D10*假设!$B$12,0) -> 24 | G10: =F10*AVERAGE(假设!$B$10,假设!$B$11) -> 840 | H10: =ROUND(D10*C10-G10,0) -> 19405 | I10: =IF(H10>=假设!$B$5,"达标（自然流口径）","差 "&TEXT(假设!$B$5-H10,"#,##0")&" 元") -> 差 595 元
A12: 怎么读这张表
A13: 1. 「日均单量」绿色 = 8 单以内（可执行）；红色 = 超过 15 单（产能上做不到）
A14: 2. 29.9 元客单需要日均 25 单 → 按已验证的 2000 观看/篇折算，需每天发 8 篇以上，不可能
A15: 3. 99 元以上客单，日均降到 8 单以内 → 这才是能规划的目标
A16: 4. 「净利(扣投流)」已扣除 40% 单量按 CAC 中值 35 元计算的投流支出

Sheet 混合客单
A1: 混合客单：现实中不会所有人都买 99 元
A2: 调「成交占比」这一列，看混合客单和所需单量怎么变。
A4: 层级 | B4: 成交占比 | C4: 客单价 | D4: 加权贡献 | F4: 指标 | G4: 值
A5: 入门层（9.9–29.9） | B5: 0.55 | C5: 25 | D5: =B5*C5 -> 13.75 | F5: 混合客单 | G5: =D8 -> 88.3
A6: 主力层（99–149） | B6: 0.35 | C6: 99 | D6: =B6*C6 -> 34.65 | F6: 净额/单 | G6: =D8*假设!$B$6 -> 75.938
A7: 高客单层（399+） | B7: 0.1 | C7: 399 | D7: =B7*C7 -> 39.9 | F7: 需成交单数/月 | G7: =ROUNDUP(假设!$B$5/(D8*假设!$B$6),0) -> 264
A8: 合计 / 混合客单 | B8: =SUM(B5:B7) -> 1 | D8: =SUM(D5:D7) -> 88.3 | F8: 日均单量 | G8: =ROUND(假设!$B$5/(D8*假设!$B$6)/假设!$B$7,1) -> 8.8
F9: 其中付费单量 | G9: =ROUND(假设!$B$5/(D8*假设!$B$6)*假设!$B$12,0) -> 105
F10: 投流支出 | G10: =ROUND(假设!$B$5/(D8*假设!$B$6)*假设!$B$12*AVERAGE(假设!$B$10,假设!$B$11),0) -> 3687
F11: 净利(扣投流) | G11: =ROUND(假设!$B$5-G10,0) -> 16313 | H11: =IF(G11>=假设!$B$5,"达标","缺口 "&TEXT(假设!$B$5-G11,"#,##0")&" 元") -> 缺口 3,687 元
A13: 关键动作：把主力层占比往上推
A14: 1. 主力层占比 35% → 混合客单约 88 元，日均约 8 单
A15: 2. 主力层占比 50% → 混合客单超过 110 元，日均降到 7 单以内
A16: 3. 所以第 2–3 个月的核心指标不是总单量，而是「主力层成交占比」
A17: 4. 把 55% 的低价买家往上推，靠三件事：详情页升级引导 / 自动回复 / 已购用户补差价升级

Sheet 投流可行性
A1: 投流可行性：什么客单价才配得起付费流量
A2: 净额必须大于获客成本，否则投一单亏一单。
A4: 客单价 | B4: 净额/单 | C4: CAC(保守 20 元) | D4: 净利 | E4: CAC(乐观 50 元) | F4: 净利 | G4: 可承受 CAC 上限 | H4: 结论
A5: 29.9 | B5: =A5*假设!$B$6 -> 25.714 | C5: =假设!$B$10 -> 20 | D5: =B5-C5 -> 5.714 | E5: =假设!$B$11 -> 50 | F5: =B5-E5 -> -24.286 | G5: =B5 -> 25.714 | H5: =IF(D5>0,"可投","每投一单亏 "&TEXT(-D5,"0")&" 元") -> 可投
A6: 49.9 | B6: =A6*假设!$B$6 -> 42.914 | C6: =假设!$B$10 -> 20 | D6: =B6-C6 -> 22.914 | E6: =假设!$B$11 -> 50 | F6: =B6-E6 -> -7.086 | G6: =B6 -> 42.914 | H6: =IF(D6>0,"可投","每投一单亏 "&TEXT(-D6,"0")&" 元") -> 可投
A7: 99 | B7: =A7*假设!$B$6 -> 85.14 | C7: =假设!$B$10 -> 20 | D7: =B7-C7 -> 65.14 | E7: =假设!$B$11 -> 50 | F7: =B7-E7 -> 35.14 | G7: =B7 -> 85.14 | H7: =IF(D7>0,"可投","每投一单亏 "&TEXT(-D7,"0")&" 元") -> 可投
A8: 149 | B8: =A8*假设!$B$6 -> 128.14 | C8: =假设!$B$10 -> 20 | D8: =B8-C8 -> 108.14 | E8: =假设!$B$11 -> 50 | F8: =B8-E8 -> 78.14 | G8: =B8 -> 128.14 | H8: =IF(D8>0,"可投","每投一单亏 "&TEXT(-D8,"0")&" 元") -> 可投
A9: 199 | B9: =A9*假设!$B$6 -> 171.14 | C9: =假设!$B$10 -> 20 | D9: =B9-C9 -> 151.14 | E9: =假设!$B$11 -> 50 | F9: =B9-E9 -> 121.14 | G9: =B9 -> 171.14 | H9: =IF(D9>0,"可投","每投一单亏 "&TEXT(-D9,"0")&" 元") -> 可投
A10: 399 | B10: =A10*假设!$B$6 -> 343.14 | C10: =假设!$B$10 -> 20 | D10: =B10-C10 -> 323.14 | E10: =假设!$B$11 -> 50 | F10: =B10-E10 -> 293.14 | G10: =B10 -> 343.14 | H10: =IF(D10>0,"可投","每投一单亏 "&TEXT(-D10,"0")&" 元") -> 可投
A12: 结论
A13: 1. 29.9 元客单：净额约 25.7 元，CAC 乐观值 50 元 → 每投一单亏约 24 元。不能投。
A14: 2. 99 元客单：净额约 85 元 → 两种 CAC 假设下都为正，可以投。
A15: 3. 149 元以上：投流空间充足，可以做「付费放量」。
A16: 4. 所以顺序必须是：先靠内容和搜索把客单做上去，再开投流。反过来做一定亏。

Sheet 三个月路线图
A1: 3 个月路线图：每月只解决一个瓶颈
A2: 不追求每月等速增长，而是每月换一个卡点去打。
A4: 月份 | B4: 本月瓶颈 | C4: 核心动作 | D4: 客单目标 | E4: 日均单量 | F4: 月净利目标 | G4: 判定线
A5: 第 1 个月 | B5: 信任与出单（0 → 首批成交） | C5: 完成银行核验填表；上架 3 个入门款；发布 15 篇；每篇带互动钩子；跑通自动发货 | D5: 25–35 元 | E5: 1–2 单 | F5: 1500–2500 元 | G5: 评论数从 0 变正数；出现单篇 1000+ 观看
A6: 第 2 个月 | B6: 客单（把人往上推） | C6: 上架全流程包 99 元；详情页加升级引导；已购用户补差价升级；主力层占比 ≥ 35% | D6: 60–90 元 | E6: 3–5 单 | F6: 6000–9000 元 | G6: 主力层成交占比 ≥ 35%；混合客单 ≥ 70 元
A7: 第 3 个月 | B7: 放量（才允许花钱） | C7: 客单站稳后开投流；主力层占比推到 50%；上 1v1 服务；复用爆款选题批量复制 | D7: 100–150 元 | E7: 6–8 单 | F7: 20000 元 | G7: 混合客单 ≥ 100 元；投流 ROI ≥ 1.5
A9: 这个路线图最重要的三条纪律
A10: 1. 第 1 个月不要碰投流。客单没上去之前，投流是纯亏损，且会把「亏损」误读成「起量」。
A11: 2. 第 2 个月不要加产品数量。瓶颈在客单，不在品类——上新只会分散账号标签。
A12: 3. 第 3 个月才是投流窗口。前提是混合客单 ≥ 100 元，此时 CAC 才有空间。
A14: 不迎合的风险声明
A15: 1. 月入 2W 是挑战目标，不是保底。第 1 个月从 0 单起步，现实区间是 1500–2500 元（与项目诊断报告的中位预期一致）。
A16: 2. 第 3 个月达成 2W 需要同时满足三件事：主力层占比 ≥ 50%、混合客单 ≥ 100 元、至少 2 篇 5000+ 观看的爆款。缺一项，落点大概率在 8000–12000 元。
A17: 3. 任何「先违规起量再整改」的想法都要排除：平台清退者永久禁止重新入驻，退出成本不可逆。
A18: 4. 主力层能否成立，取决于你能否交付「一次简历诊断」这类人工服务。做不到就改用「定制改写建议」，但仍需你本人处理。
