Workbook

Sheet 假设与口径
A1: 假设与口径（唯一参数源 · 全部测算引用本表）
A2: 替换作战室文档中「本月目标 · 净利 5000 执行方案」的旧口径。淡橙色为可调参数。
A3: 参数 | B3: 值 | C3: 单位 | D3: 说明 / 与旧口径差异
A4: 净利目标 | B4: 5000 | C4: 元 | D4: 维持目标不变，但按三档呈现（保底/目标/挑战）
A5: 执行期天数 | B5: 22 | C5: 天 | D5: 10/09–10/31
A6: 平台服务费（常规） | B6: 0.02 | C6: 比例 | D6: 旧口径按 5% 计提，偏高。虚拟商品常规 2%
A7: 平台服务费（百万免佣期） | B7: 0.006 | C7: 比例 | D7: 2025-09-01 至 2026-08-31：前 100 万交易额免佣，仅留支付渠道成本 0.6%
A8: 退款损耗（低） | B8: 0.08 | C8: 比例 | D8: 旧口径按 5% 计提，偏低
A9: 退款损耗（中） | B9: 0.12 | C9: 比例 | D9: ← 到账率由本行退款口径驱动
A10: 退款损耗（高） | B10: 0.18 | C10: 比例 | D10: 悲观情景：出现集中退款或差评
A11: 背景口径 | B11: 0.02 | C11: 文本 | D11: 用于本表全部测算，偏保守（未享免佣）
A12: 退款口径 | B12: 0.12 | C12: 文本 | D12: 用于本表全部测算，取推荐基准
A14: 客单档位 | B14: 客单价 | C14: 到账率 | D14: 净额/单 | E14: 备注
A15: 简历包基础 | B15: 9.9 | C15: =1-$B$9 -> 0.88 | D15: =B15*C15 -> 8.712 | E15: 低客单，单独卖不划算
A16: 时间表单卖 | B16: 19.9 | C16: =1-$B$9 -> 0.88 | D16: =B16*C16 -> 17.512 | E16: 引流与信任款
A17: 组合包（主推） | B17: 25.9 | C17: =1-$B$9 -> 0.88 | D17: =B17*C17 -> 22.792 | E17: 目标口径
A18: 组合包升级 | B18: 29.9 | C18: =1-$B$9 -> 0.88 | D18: =B18*C18 -> 26.312 | E18: 第 3 周上，冲客单
A19: 高客单咨询 | B19: 599 | C19: =1-$B$9 -> 0.88 | D19: =B19*C19 -> 527.12 | E19: 虚拟服务，验证付费意愿用
A21: 数据来源
A22: 1. 平台服务费 2% / 百万免佣 0.6%：小红书虚拟行业经营指南、百万免佣计划公开报道
A23: 2. 退款损耗 8–12%：虚拟商品退款争议普遍存在；实操记录显示退款会致「店铺分爆红、订单量腰斩、商品笔记停止推流」
A24: 3. 因此退款不只是损失一单的金额，而是连锁影响后续流量 —— 旧口径按 5% 计提低估了风险

Sheet 本月目标
A1: 本月目标换算（22 天 · 10/09–10/31）
A2: 目标 = 5000 元净利。先选客单档位，再看所需日均单量。
A4: 客单档位 | B4: 客单价 | C4: 净额/单 | D4: 所需单量 | E4: 日均单量 | F4: 判断
A5: 简历包基础 | B5: 9.9 | C5: =B5*假设与口径!$C$15 -> 8.712 | D5: =IF(C5<=0,"不可达",ROUNDUP(5000/C5,0)) -> 574 | E5: =IF(C5<=0,"—",ROUND(D5/22,1)) -> 26.1 | F5: 低客单，单独卖不划算
A6: 时间表单卖 | B6: 19.9 | C6: =B6*假设与口径!$C$15 -> 17.512 | D6: =IF(C6<=0,"不可达",ROUNDUP(5000/C6,0)) -> 286 | E6: =IF(C6<=0,"—",ROUND(D6/22,1)) -> 13 | F6: 引流与信任款
A7: 组合包（主推） | B7: 25.9 | C7: =B7*假设与口径!$C$15 -> 22.792 | D7: =IF(C7<=0,"不可达",ROUNDUP(5000/C7,0)) -> 220 | E7: =IF(C7<=0,"—",ROUND(D7/22,1)) -> 10 | F7: 目标口径
A8: 组合包升级 | B8: 29.9 | C8: =B8*假设与口径!$C$15 -> 26.312 | D8: =IF(C8<=0,"不可达",ROUNDUP(5000/C8,0)) -> 191 | E8: =IF(C8<=0,"—",ROUND(D8/22,1)) -> 8.7 | F8: 第 3 周上，冲客单
A9: 高客单咨询 | B9: 599 | C9: =B9*假设与口径!$C$15 -> 527.12 | D9: =IF(C9<=0,"不可达",ROUNDUP(5000/C9,0)) -> 10 | E9: =IF(C9<=0,"—",ROUND(D9/22,1)) -> 0.5 | F9: 虚拟服务，验证付费意愿用
A10: 与旧口径的差异（客单 15 元 / 25.9 元）
A11: 口径 | B11: 客单价 | C11: 旧文档单量 | D11: 旧文档日均 | E11: 重算单量 | F11: 重算日均
A12: 组合包 | B12: 25.9 | C12: 214 | D12: 7.1 | E12: =ROUNDUP(5000/(B12*假设与口径!$C$15),0) -> 220 | F12: =ROUND(E12/22,1) -> 10
A13: 混卖实际客单 | B13: 15 | C13: 370 | D13: 12.3 | E13: =ROUNDUP(5000/(B13*假设与口径!$C$15),0) -> 379 | F13: =ROUND(E13/22,1) -> 17.2
A14: 结论：客单 15 元时日均需约 20 单，对 26 粉新号属结构性不可能 →「把客单做到 25 元以上」是目标成立的前提。

Sheet 含投流测算
A1: 付费流量测算：25.9 元客单能不能投流？
A2: 薯条没有营销组件（只能买阅读/点赞/关注）；聚光起充 5000 元以上、日最低预算 300 元。以下按聚光 CPC 口径测算。
A4: 行业基准 | B4: 值 | C4: 说明
A5: CPC（元/点击） | B5: 0.8 | C5: 代理商口径下限
A6: CPC（元/点击） | B6: 4 | C6: 代理商口径上限
A7: 点击→下单转化（低） | B7: 0.02 | C7: 资料类保守值
A8: 点击→下单转化（高） | B8: 0.05 | C8: 乐观值
A9: 获客成本与净利（每个客单档位 × 四种组合）
A10: 客单档位 | B10: 客单价 | C10: 净额/单 | D10: CAC(低CPC高转化) | E10: 净利/单 | F10: CAC(高CPC低转化) | G10: 净利/单 | H10: 盈亏平衡CAC | I10: 结论
A11: 简历包基础 | B11: 9.9 | C11: =B11*假设与口径!$C$15 -> 8.712 | D11: =$B$5/$B$8 -> 16 | E11: =C11-D11 -> -7.288 | F11: =$B$6/$B$7 -> 200 | G11: =C11-F11 -> -191.288 | H11: =C11 -> 8.712 | I11: =IF(E11<0,"每投一单亏 "&TEXT(-E11,"0")&" 元","可投") -> 每投一单亏 7 元
A12: 时间表单卖 | B12: 19.9 | C12: =B12*假设与口径!$C$15 -> 17.512 | D12: =$B$5/$B$8 -> 16 | E12: =C12-D12 -> 1.512 | F12: =$B$6/$B$7 -> 200 | G12: =C12-F12 -> -182.488 | H12: =C12 -> 17.512 | I12: =IF(E12<0,"每投一单亏 "&TEXT(-E12,"0")&" 元","可投") -> 可投
A13: 组合包（主推） | B13: 25.9 | C13: =B13*假设与口径!$C$15 -> 22.792 | D13: =$B$5/$B$8 -> 16 | E13: =C13-D13 -> 6.792 | F13: =$B$6/$B$7 -> 200 | G13: =C13-F13 -> -177.208 | H13: =C13 -> 22.792 | I13: =IF(E13<0,"每投一单亏 "&TEXT(-E13,"0")&" 元","可投") -> 可投
A14: 组合包升级 | B14: 29.9 | C14: =B14*假设与口径!$C$15 -> 26.312 | D14: =$B$5/$B$8 -> 16 | E14: =C14-D14 -> 10.312 | F14: =$B$6/$B$7 -> 200 | G14: =C14-F14 -> -173.688 | H14: =C14 -> 26.312 | I14: =IF(E14<0,"每投一单亏 "&TEXT(-E14,"0")&" 元","可投") -> 可投
A15: 高客单咨询 | B15: 599 | C15: =B15*假设与口径!$C$15 -> 527.12 | D15: =$B$5/$B$8 -> 16 | E15: =C15-D15 -> 511.12 | F15: =$B$6/$B$7 -> 200 | G15: =C15-F15 -> 327.12 | H15: =C15 -> 527.12 | I15: =IF(E15<0,"每投一单亏 "&TEXT(-E15,"0")&" 元","可投") -> 可投
A17: 要在本价格带上投正，需要同时满足
A18: ① 净额/单 > CAC；② 点击→下单转化 > CPC ÷ 净额/单。以主推组合包（25.9 元）为例：
A20: ="① CPC = 4 元时，所需转化率 > "&TEXT(C27,"0.0%")&"（公开资料中找不到支撑）" -> ① CPC = 4 元时，所需转化率 > 17.6%（公开资料中找不到支撑）
A21: ="② 转化率 5% 时，可承受 CPC 上限约 "&TEXT(C26,"0.00")&" 元" -> ② 转化率 5% 时，可承受 CPC 上限约 1.14 元
A22: 结论：本项目在 19.9–25.9 元价格带上，付费投流在数学上不成立，应转搜索关键词 + 群聊。
A24: 结论计算块（可改） | B24: 主推客单价 | C24: 25.9
B25: 净额/单 | C25: =C24*假设与口径!$C$15 -> 22.792
B26: CPC 上限（转化 5%） | C26: =C25*$B$8 -> 1.1396
B27: CPC=4 元时所需转化率 | C27: =$B$6/C25 -> 0.17550018

Sheet 净利敏感性
A1: 净利敏感性：22 天 × 不同客单 × 不同日均单量
A2: 绿色 = 达成 5000 目标的组合；浅橙 = 低于 2500。列按客单价，行按日均单量。
A3: 日均单量 | B3: 9.9 | C3: 15 | D3: 19.9 | E3: 25.9 | F3: 29.9
A4: 3 | B4: =ROUND($A4*22*B$3*假设与口径!$C$15,0) -> 575 | C4: =ROUND($A4*22*C$3*假设与口径!$C$15,0) -> 871 | D4: =ROUND($A4*22*D$3*假设与口径!$C$15,0) -> 1156 | E4: =ROUND($A4*22*E$3*假设与口径!$C$15,0) -> 1504 | F4: =ROUND($A4*22*F$3*假设与口径!$C$15,0) -> 1737
A5: 5 | B5: =ROUND($A5*22*B$3*假设与口径!$C$15,0) -> 958 | C5: =ROUND($A5*22*C$3*假设与口径!$C$15,0) -> 1452 | D5: =ROUND($A5*22*D$3*假设与口径!$C$15,0) -> 1926 | E5: =ROUND($A5*22*E$3*假设与口径!$C$15,0) -> 2507 | F5: =ROUND($A5*22*F$3*假设与口径!$C$15,0) -> 2894
A6: 7 | B6: =ROUND($A6*22*B$3*假设与口径!$C$15,0) -> 1342 | C6: =ROUND($A6*22*C$3*假设与口径!$C$15,0) -> 2033 | D6: =ROUND($A6*22*D$3*假设与口径!$C$15,0) -> 2697 | E6: =ROUND($A6*22*E$3*假设与口径!$C$15,0) -> 3510 | F6: =ROUND($A6*22*F$3*假设与口径!$C$15,0) -> 4052
A7: 10 | B7: =ROUND($A7*22*B$3*假设与口径!$C$15,0) -> 1917 | C7: =ROUND($A7*22*C$3*假设与口径!$C$15,0) -> 2904 | D7: =ROUND($A7*22*D$3*假设与口径!$C$15,0) -> 3853 | E7: =ROUND($A7*22*E$3*假设与口径!$C$15,0) -> 5014 | F7: =ROUND($A7*22*F$3*假设与口径!$C$15,0) -> 5789
A8: 15 | B8: =ROUND($A8*22*B$3*假设与口径!$C$15,0) -> 2875 | C8: =ROUND($A8*22*C$3*假设与口径!$C$15,0) -> 4356 | D8: =ROUND($A8*22*D$3*假设与口径!$C$15,0) -> 5779 | E8: =ROUND($A8*22*E$3*假设与口径!$C$15,0) -> 7521 | F8: =ROUND($A8*22*F$3*假设与口径!$C$15,0) -> 8683
A9: 20 | B9: =ROUND($A9*22*B$3*假设与口径!$C$15,0) -> 3833 | C9: =ROUND($A9*22*C$3*假设与口径!$C$15,0) -> 5808 | D9: =ROUND($A9*22*D$3*假设与口径!$C$15,0) -> 7705 | E9: =ROUND($A9*22*E$3*假设与口径!$C$15,0) -> 10028 | F9: =ROUND($A9*22*F$3*假设与口径!$C$15,0) -> 11577
A10: 25 | B10: =ROUND($A10*22*B$3*假设与口径!$C$15,0) -> 4792 | C10: =ROUND($A10*22*C$3*假设与口径!$C$15,0) -> 7260 | D10: =ROUND($A10*22*D$3*假设与口径!$C$15,0) -> 9632 | E10: =ROUND($A10*22*E$3*假设与口径!$C$15,0) -> 12536 | F10: =ROUND($A10*22*F$3*假设与口径!$C$15,0) -> 14472
A12: 备注
A13: 1. 净额/单 = 客单价 × 到账率（到账率取自「假设与口径」，当前为 88%：2% 平台服务费 + 12% 退款）
A14: 2. 表中为 22 天累计净利。绿色达成 5000，浅橙低于 2500（文档自认的中位预期区间上限）
A15: 3. 对照：账号当前单篇最高观看 799；历史最高曝光 2051（观看约 280）→ 日均 7–10 单需要稳定爆款

Sheet 三周进度表
A1: 三周进度表与判定线（按 5000 元目标折算）
A2: 判定线已按剔除平台 5% 假设、采用 88% 到账率重算；客单基准 25.9 元。
A4: 阶段 | B4: 日期 | C4: 天数 | D4: 阶段目标 | E4: 阶段单量 | F4: 累计单量 | G4: 累计净利 | H4: 文档原判定线 | I4: 判定
A5: 第 1 周 · 起量 | B5: 10/09–10/15 | C5: 7 | D5: 日均 10.0 单 | E5: 70 | F5: 70 | G5: =ROUND(F5*25.9*假设与口径!$C$15,0) -> 1595 | H5: — | I5: 按累计净利对照 5000
A6: 第 2 周 · 冲刺 | B6: 10/16–10/22 | C6: 7 | D6: 日均 10.0 单 | E6: 70 | F6: 140 | G6: =ROUND(F6*25.9*假设与口径!$C$15,0) -> 3191 | H6: 10/16 判定线 | I6: 按累计净利对照 5000
A7: 第 3 周 · 收官 | B7: 10/23–10/31 | C7: 9 | D7: 日均 10.0 单 | E7: 90 | F7: 230 | G7: =ROUND(F7*25.9*假设与口径!$C$15,0) -> 5242 | H7: 10/23 判定线 | I7: 按累计净利对照 5000
A9: 原判定线的问题
A10: 1. 文档 10/16 判定线「单量 ≥ 60」——60 单 × 25.9 元 × 88% ≈ 1368 元，只对应「净利约 1400 元」的档位
A11: 2. 若按 60 单放行，等于把目标默认降到 1400 元，却仍按 5000 元的节奏分配资源
A12: 3. 建议判定线：10/16 累计 ≥ 68 单且客单 ≥ 20；10/23 累计 ≥ 157 单
A13: 4. 目标分层建议：保底 1200 元 / 目标 2500 元 / 挑战 5000 元
A14: 5. 末行累计净利约 5242 元，略高于目标：因阶段单量四舍五入（70/70/90 = 230 单，非恰好 220 单），属取整残差，不是计算错误

Sheet 口径修正对照
A1: 与旧文档口径的逐项修正对照
A3: 项目 | B3: 旧文档口径 | C3: 修正口径 | D3: 方向 | E3: 依据
A4: 平台扣点 | B4: 5% | C4: 0.6%–2%（当前免佣期 0.6%） | D4: 利好 | E4: 虚拟商品常规服务费 2%；百万免佣计划前 100 万交易额仅 0.6% 支付成本
A5: 退款损耗 | B5: 5% | C5: 8%–12%（推荐 12%） | D5: 利空 | E5: 虚拟商品退款争议普遍；退款致店铺分下降会连累流量
A6: 客单假设 | B6: 只给标价 25.9 | C6: 同时给 15 元混卖实际客单 | D6: 利空 | E6: 文档自述「现状 15 元（9.9+19.9 混卖）」
A7: 投流成本 | B7: 未计入 | C7: CAC 40–100 元/单（负毛利） | D7: 利空 | E7: CPC 0.8–4 元 × 点击→下单 2–5%
A8: 投流工具 | B8: 薯条（商品成交目标） | C8: 薯条无商品组件；聚光起充 5000 元 | D8: 利空 | E8: 薯条仅三种推广目标；聚光需企业号
A9: 10/16 判定线 | B9: 单量 ≥ 60 | C9: ≥ 68 单且客单 ≥ 20 | D9: 利空 | E9: 60 单仅对应约 1400 元净利
A10: 净利/单（25.9 元） | B10: 23.3 元（扣 10%） | C10: 22.8 元（扣 12%） | D10: 基本持平 | E10: 两项修正方向相反，大体抵消
A12: 核心结论
A13: 1. 两项财务修正方向相反、大体抵消：净额/单仍约 22.8 元，日均约 10 单（25.9 元客单）。
A14: 2. 真正的风险不是费率，而是：① 真实客单可能只有 15 元（日均需约 20 单）；② 付费流量负毛利；③ 退款连累店铺分。
A15: 3. 因此策略应为：提客单（做分层与组合）+ 零成本流量（搜索关键词 + 群聊）+ 严控退款（交付说明前置）。
